garf/community/google/knowledge_graph/__init__.py
garf/community/google/knowledge_graph/api_clients.py
garf/community/google/knowledge_graph/query_editor.py
garf/community/google/knowledge_graph/report_fetcher.py
garf_knowledge_graph_api/__init__.py
garf_knowledge_graph_api/api_clients.py
garf_knowledge_graph_api/query_editor.py
garf_knowledge_graph_api/report_fetcher.py
garf_knowledge_graph_api-1.0.0.dist-info/METADATA
garf_knowledge_graph_api-1.0.0.dist-info/WHEEL
garf_knowledge_graph_api-1.0.0.dist-info/entry_points.txt
garf_knowledge_graph_api-1.0.0.dist-info/top_level.txt
garf_knowledge_graph_api-1.0.0.dist-info/RECORD
